shipyard_trello/__init__.py
shipyard_trello/cli/add_comment.py
shipyard_trello/cli/create_card.py
shipyard_trello/cli/edit_card.py
shipyard_trello/trello.py
shipyard_trello-0.1.1.dist-info/METADATA
shipyard_trello-0.1.1.dist-info/WHEEL
shipyard_trello-0.1.1.dist-info/RECORD
